precilaser/__init__.py
precilaser/amplifier.py
precilaser/check.py
precilaser/device.py
precilaser/enums.py
precilaser/message.py
precilaser/py.typed
precilaser/seed.py
precilaser/status.py
precilaser/utils.py
precilaser-0.1.2.dist-info/LICENSE
precilaser-0.1.2.dist-info/WHEEL
precilaser-0.1.2.dist-info/METADATA
precilaser-0.1.2.dist-info/RECORD
