Metadata-Version: 2.1
Name: precilaser
Version: 0.1.2
Summary: 
Home-page: https://github.com/ograsdijk/precilaser
License: MIT
Author: ograsdijk
Author-email: o.grasdijk@gmail.com
Requires-Python: >=3.7,<4.0
Classifier: License :: OSI Approved :: MIT License
Classifier: Programming Language :: Python :: 3
Classifier: Programming Language :: Python :: 3.7
Classifier: Programming Language :: Python :: 3.8
Classifier: Programming Language :: Python :: 3.9
Classifier: Programming Language :: Python :: 3.10
Requires-Dist: PyVISA (>=1.12.0,<2.0.0)
Requires-Dist: rich (>=13.3.3,<14.0.0)
Project-URL: Repository, https://github.com/ograsdijk/precilaser
